unicode_sanity/__init__.py
unicode_sanity/cli.py
unicode_sanity/core.py
unicode_sanity-0.1.0.dist-info/METADATA
unicode_sanity-0.1.0.dist-info/WHEEL
unicode_sanity-0.1.0.dist-info/entry_points.txt
unicode_sanity-0.1.0.dist-info/licenses/LICENSE
unicode_sanity-0.1.0.dist-info/RECORD
