Metadata-Version: 2.4
Name: unicode-sanity
Version: 0.1.0
Summary: Clean invisible/control Unicode characters, normalize text, and optionally convert/remove emoji — with an explainable report.
Project-URL: Homepage, https://github.com/EklavyaT/unicode-sanity
Project-URL: Repository, https://github.com/EklavyaT/unicode-sanity
Author: Eklavya Tomar
License: MIT License
License-File: LICENSE
Keywords: bidi,emoji,normalization,text-cleaning,unicode,zero-width
Classifier: Intended Audience :: Developers
Classifier: License :: OSI Approved :: MIT License
Classifier: Operating System :: OS Independent
Classifier: Programming Language :: Python :: 3
Classifier: Programming Language :: Python :: 3 :: Only
Classifier: Programming Language :: Python :: 3.9
Classifier: Programming Language :: Python :: 3.10
Classifier: Programming Language :: Python :: 3.11
Classifier: Programming Language :: Python :: 3.12
Classifier: Programming Language :: Python :: 3.13
Classifier: Topic :: Text Processing :: Filters
Classifier: Topic :: Utilities
Requires-Python: >=3.9
Requires-Dist: emoji>=2.8.0
